[{"model": "news.category", "pk": 1, "fields": {"name": "\uc815\uce58", "inter_users": []}}, {"model": "news.category", "pk": 2, "fields": {"name": "\uacbd\uc81c", "inter_users": []}}, {"model": "news.category", "pk": 3, "fields": {"name": "\uc0ac\ud68c", "inter_users": []}}, {"model": "news.category", "pk": 4, "fields": {"name": "\ubb38\ud654", "inter_users": []}}, {"model": "news.category", "pk": 5, "fields": {"name": "\uc138\uacc4", "inter_users": []}}, {"model": "news.category", "pk": 6, "fields": {"name": "IT", "inter_users": []}}]